{
	"name": "Q3",
	"properties": {
		"type": "MappingDataFlow",
		"typeProperties": {
			"sources": [
				{
					"dataset": {
						"referenceName": "ConditionSource",
						"type": "DatasetReference"
					},
					"name": "source1"
				}
			],
			"sinks": [
				{
					"dataset": {
						"referenceName": "Json1",
						"type": "DatasetReference"
					},
					"name": "sink1"
				},
				{
					"dataset": {
						"referenceName": "Json2",
						"type": "DatasetReference"
					},
					"name": "sink2"
				},
				{
					"dataset": {
						"referenceName": "Json3",
						"type": "DatasetReference"
					},
					"name": "sink3"
				}
			],
			"transformations": [
				{
					"name": "ConditionalSplit1"
				}
			],
			"script": "source(output(\n\t\tProductID as integer,\n\t\tName as string,\n\t\tProductNumber as string,\n\t\tColor as string,\n\t\tStandardCost as decimal(19,4),\n\t\tListPrice as decimal(19,4),\n\t\tSize as string,\n\t\tWeight as decimal(8,2),\n\t\tProductCategoryID as integer,\n\t\tProductModelID as integer,\n\t\tSellStartDate as timestamp,\n\t\tSellEndDate as timestamp,\n\t\tDiscontinuedDate as timestamp,\n\t\tThumbNailPhoto as binary,\n\t\tThumbnailPhotoFileName as string,\n\t\trowguid as string,\n\t\tModifiedDate as timestamp\n\t),\n\tallowSchemaDrift: true,\n\tvalidateSchema: false,\n\tisolationLevel: 'READ_UNCOMMITTED',\n\tformat: 'table') ~> source1\nsource1 split(ProductID<=700,\n\tProductID>700 && ProductID<800,\n\tdisjoint: false) ~> ConditionalSplit1@(L, B, Remaining)\nConditionalSplit1@L sink(allowSchemaDrift: true,\n\tvalidateSchema: false,\n\tskipDuplicateMapInputs: true,\n\tskipDuplicateMapOutputs: true) ~> sink1\nConditionalSplit1@Remaining sink(allowSchemaDrift: true,\n\tvalidateSchema: false,\n\tskipDuplicateMapInputs: true,\n\tskipDuplicateMapOutputs: true) ~> sink2\nConditionalSplit1@B sink(allowSchemaDrift: true,\n\tvalidateSchema: false,\n\tskipDuplicateMapInputs: true,\n\tskipDuplicateMapOutputs: true) ~> sink3"
		}
	}
}